{
 "charts": [],
 "content": "[{\"id\":\"3ekXzXDNpa\",\"type\":\"header\",\"data\":{\"text\":\"<span class=\\\"h4\\\"><b>Acc\u00e8s rapide</b></span>\",\"col\":12}},{\"id\":\"GiBt27RDSR\",\"type\":\"shortcut\",\"data\":{\"shortcut_name\":\"Blog Post\",\"col\":3}},{\"id\":\"ocqvMDDGsA\",\"type\":\"shortcut\",\"data\":{\"shortcut_name\":\"Blogger\",\"col\":3}},{\"id\":\"qDxUkgoiNs\",\"type\":\"shortcut\",\"data\":{\"shortcut_name\":\"Web Page\",\"col\":3}},{\"id\":\"0l11_pJCVj\",\"type\":\"shortcut\",\"data\":{\"shortcut_name\":\"Popup\",\"col\":3}},{\"id\":\"9CWTnGUjDh\",\"type\":\"shortcut\",\"data\":{\"shortcut_name\":\"View Website\",\"col\":3}},{\"id\":\"2XzH0HGoLF\",\"type\":\"shortcut\",\"data\":{\"shortcut_name\":\"View Ecommerce\",\"col\":3}},{\"id\":\"Nnj4IF-GmJ\",\"type\":\"shortcut\",\"data\":{\"shortcut_name\":\"View Blog\",\"col\":3}},{\"id\":\"vigHLnZglJ\",\"type\":\"custom_block\",\"data\":{\"custom_block_name\":\"Google Site Kit\",\"col\":3}},{\"id\":\"YPOEPR6CvZ\",\"type\":\"spacer\",\"data\":{\"col\":12}},{\"id\":\"0xSRLJWacV\",\"type\":\"header\",\"data\":{\"text\":\"<span class=\\\"h4\\\"><b>Activer et d\u00e9sactiver</b></span>\",\"col\":12}},{\"id\":\"KNTcoSU_S3\",\"type\":\"custom_block\",\"data\":{\"custom_block_name\":\"Active website and ecommerce\",\"col\":3}},{\"id\":\"dyv3Iep2Rk\",\"type\":\"spacer\",\"data\":{\"col\":12}},{\"id\":\"fOUdrhsmE0\",\"type\":\"header\",\"data\":{\"text\":\"<span class=\\\"h4\\\"><b>Menu</b><span class=\\\"ml-2 collapse-indicator mb-1\\\" style=\\\"\\\"></span></span>\",\"col\":12}},{\"id\":\"JQZzcMKnOP\",\"type\":\"card\",\"data\":{\"card_name\":\"Ecommerce\",\"col\":4}},{\"id\":\"8aQ7Jj00Jh\",\"type\":\"card\",\"data\":{\"card_name\":\"Blog\",\"col\":4}},{\"id\":\"IDW7UZ6Lhm\",\"type\":\"card\",\"data\":{\"card_name\":\"Page &amp; Popup\",\"col\":4}},{\"id\":\"My6LLh4Rmy\",\"type\":\"card\",\"data\":{\"card_name\":\"Menu\",\"col\":4}},{\"id\":\"D-wYoYn00j\",\"type\":\"card\",\"data\":{\"card_name\":\"Website\",\"col\":4}},{\"id\":\"gPuMfTX2qf\",\"type\":\"card\",\"data\":{\"card_name\":\"Settings\",\"col\":4}}]",
 "creation": "2022-03-07 17:13:48.842648",
 "custom_blocks": [],
 "docstatus": 0,
 "doctype": "Workspace",
 "for_user": "",
 "hide_custom": 0,
 "icon": "website",
 "idx": 0,
 "is_hidden": 0,
 "label": "Website",
 "links": [],
 "modified": "2024-05-14 22:31:16.723634",
 "modified_by": "Administrator",
 "module": "Website",
 "name": "Website",
 "number_cards": [],
 "owner": "Administrator",
 "parent_page": "",
 "public": 1,
 "quick_lists": [],
 "restrict_to_domain": "Website",
 "roles": [],
 "sequence_id": 55.0,
 "shortcuts": [],
 "title": "Website"
}